README.md
setup.py
north_c9/__init__.py
north_c9/__version__.py
north_c9/axis.py
north_c9/controller.py
north_c9/joysticks.py
north_c9/sequences.py
north_c9/serial.py
north_c9.egg-info/PKG-INFO
north_c9.egg-info/SOURCES.txt
north_c9.egg-info/dependency_links.txt
north_c9.egg-info/requires.txt
north_c9.egg-info/top_level.txt
tests/integration_tests/__init__.py
tests/integration_tests/test_basic_movement.py
tests/integration_tests/test_capping.py
tests/integration_tests/test_com.py
tests/integration_tests/test_controller.py
tests/integration_tests/test_deck.py
tests/integration_tests/test_elbow_swap.py
tests/unit_tests/__init__.py
tests/unit_tests/test_client.py
tests/unit_tests/test_grid.py
tests/unit_tests/test_home.py
tests/unit_tests/test_kinematics.py
tests/unit_tests/test_location.py
tests/unit_tests/test_modbus.py
tests/unit_tests/test_movement_and_modbus.py
tests/unit_tests/test_protocol.py
tests/unit_tests/test_robot.py
tests/unit_tests/test_trajectory.py