Metadata-Version: 2.1
Name: north-c9
Version: 0.3.8
Summary: A low-level communication library for the North C9 controller.
Home-page: https://gitlab.com/north-robotics/north_c9
Author: Sean Clark
Author-email: sclark@northrobotics.com
License: MIT
Platform: UNKNOWN
Requires-Python: >=3.6.0
